{
  "definitions": {
    "RequestProtocol": {
      "type": "object",
      "properties": {
        "requestId": {
          "type": "number"
        },
        "kind": {
          "type": "string",
          "enum": [
            "search logs",
            "search samples",
            "resave failed logs"
          ]
        },
        "searchLogs": {
          "$ref": "#/definitions/SearchLogs"
        },
        "searchSamples": {
          "$ref": "#/definitions/SearchSamples"
        }
      },
      "required": [
        "requestId",
        "kind"
      ],
      "additionalProperties": false,
      "maxProperties": 3
    },
    "SearchLogs": {
      "type": "object",
      "properties": {
        "content": {
          "type": "string"
        },
        "time": {
          "type": "string"
        },
        "hostname": {
          "type": "string"
        },
        "from": {
          "type": "number"
        },
        "size": {
          "type": "number"
        }
      },
      "required": [
        "content",
        "time",
        "hostname",
        "from",
        "size"
      ],
      "additionalProperties": false
    },
    "SearchSamples": {
      "type": "object",
      "properties": {
        "from": {
          "type": "string"
        },
        "to": {
          "type": "string"
        }
      },
      "required": [
        "from",
        "to"
      ],
      "additionalProperties": false
    },
    "ResponseProtocol": {
      "type": "object",
      "properties": {
        "kind": {
          "type": "string",
          "enum": [
            "flows",
            "history samples",
            "search logs result",
            "search samples result",
            "resave failed logs result"
          ]
        },
        "flows": {
          "$ref": "#/definitions/Flows"
        },
        "historySamples": {
          "type": "array",
          "items": {
            "$ref": "#/definitions/SampleFrame"
          }
        },
        "searchLogsResult": {
          "$ref": "#/definitions/SearchLogsResult"
        },
        "searchSamplesResult": {
          "$ref": "#/definitions/SearchSamplesResult"
        },
        "resaveFailedLogsResult": {
          "$ref": "#/definitions/ResaveFailedLogsResult"
        }
      },
      "required": [
        "kind"
      ],
      "additionalProperties": false,
      "maxProperties": 2
    },
    "Flows": {
      "type": "object",
      "properties": {
        "serverTime": {
          "type": "string"
        },
        "flows": {
          "type": "array",
          "items": {
            "$ref": "#/definitions/Flow"
          }
        }
      },
      "required": [
        "serverTime",
        "flows"
      ],
      "additionalProperties": false
    },
    "SearchLogsResult": {
      "type": "object",
      "properties": {
        "requestId": {
          "type": "number"
        },
        "kind": {
          "type": "string",
          "enum": [
            "success",
            "fail"
          ]
        },
        "total": {
          "type": "number"
        },
        "logs": {
          "type": "array",
          "items": {
            "$ref": "#/definitions/Log"
          }
        },
        "error": {
          "type": "string"
        }
      },
      "required": [
        "requestId",
        "kind"
      ],
      "additionalProperties": false,
      "minProperties": 3,
      "maxProperties": 4
    },
    "SearchSamplesResult": {
      "type": "object",
      "properties": {
        "requestId": {
          "type": "number"
        },
        "kind": {
          "type": "string",
          "enum": [
            "success",
            "fail"
          ]
        },
        "searchSampleResult": {
          "type": "array",
          "items": {
            "$ref": "#/definitions/SampleFrame"
          }
        },
        "error": {
          "type": "string"
        }
      },
      "required": [
        "requestId",
        "kind"
      ],
      "additionalProperties": false,
      "maxProperties": 3
    },
    "ResaveFailedLogsResult": {
      "type": "object",
      "properties": {
        "requestId": {
          "type": "number"
        },
        "kind": {
          "type": "string",
          "enum": [
            "success",
            "fail"
          ]
        },
        "savedCount": {
          "type": "number"
        },
        "totalCount": {
          "type": "number"
        },
        "error": {
          "type": "string"
        }
      },
      "required": [
        "requestId",
        "kind"
      ],
      "additionalProperties": false,
      "minProperties": 3,
      "maxProperties": 4
    },
    "SampleFrame": {
      "type": "object",
      "properties": {
        "time": {
          "type": "string"
        },
        "samples": {
          "type": "array",
          "items": {
            "$ref": "#/definitions/Sample"
          }
        }
      },
      "required": [
        "time"
      ],
      "additionalProperties": false
    },
    "FlowProtocol": {
      "type": "object",
      "properties": {
        "flows": {
          "type": "array",
          "items": {
            "$ref": "#/definitions/Flow"
          }
        }
      },
      "required": [
        "flows"
      ],
      "additionalProperties": false
    },
    "Flow": {
      "type": "object",
      "properties": {
        "kind": {
          "type": "string",
          "enum": [
            "log",
            "sample"
          ]
        },
        "log": {
          "$ref": "#/definitions/Log"
        },
        "sample": {
          "$ref": "#/definitions/Sample"
        }
      },
      "required": [
        "kind"
      ],
      "additionalProperties": false,
      "minProperties": 2,
      "maxProperties": 2
    },
    "Log": {
      "type": "object",
      "properties": {
        "time": {
          "type": "string"
        },
        "content": {
          "type": "string"
        },
        "filepath": {
          "type": "string"
        },
        "hostname": {
          "type": "string"
        }
      },
      "required": [
        "time",
        "content",
        "filepath",
        "hostname"
      ],
      "additionalProperties": false
    },
    "Sample": {
      "type": "object",
      "properties": {
        "hostname": {
          "type": "string"
        },
        "port": {
          "type": "number"
        },
        "values": {
          "type": "object",
          "additionalProperties": {
            "type": "number"
          }
        }
      },
      "required": [
        "hostname",
        "values"
      ],
      "additionalProperties": false
    }
  },
  "$ref": "#/definitions/FlowProtocol"
}